tokensjar/__init__.py
tokensjar/tokensjar.py
tokensjar-1.1.0.dist-info/LICENSE
tokensjar-1.1.0.dist-info/METADATA
tokensjar-1.1.0.dist-info/WHEEL
tokensjar-1.1.0.dist-info/top_level.txt
tokensjar-1.1.0.dist-info/RECORD
