Metadata-Version: 2.1
Name: tokensjar
Version: 1.1.0
Summary: A micro token interpretor/manipulator for Python
Home-page: https://github.com/tcladet/tokensjar
Author: Tristan Cladet
Author-email: tristan.cladet@gmail.com
Project-URL: Bug Tracker, https://github.com/tcladet/tokensjar
Classifier: Programming Language :: Python :: 3.11
Classifier: License :: OSI Approved :: GNU General Public License v3 (GPLv3)
Classifier: Operating System :: OS Independent
Requires-Python: >=3.11
License-File: LICENSE
